wildtorch/__about__.py
wildtorch/__init__.py
wildtorch/dataset.py
wildtorch/logger.py
wildtorch/main.py
wildtorch/metrics.py
wildtorch/utils.py
wildtorch-1.0.0b1.dist-info/METADATA
wildtorch-1.0.0b1.dist-info/WHEEL
wildtorch-1.0.0b1.dist-info/licenses/LICENSE
wildtorch-1.0.0b1.dist-info/RECORD
