Metadata-Version: 2.3
Name: wildtorch
Version: 1.0.0b1
Summary: WildTorch: Leveraging GPU Acceleration for High-Fidelity, Stochastic Wildfire Simulations with PyTorch
Project-URL: Documentation, https://github.com/xiazeyu/WildTorch#readme
Project-URL: Issues, https://github.com/xiazeyu/WildTorch/issues
Project-URL: Source, https://github.com/xiazeyu/WildTorch
Author-email: Zeyu Xia <i@xiaze.pro>
License: MIT License
License-File: LICENSE
Classifier: Development Status :: 3 - Alpha
Classifier: Environment :: GPU
Classifier: Intended Audience :: Science/Research
Classifier: License :: OSI Approved :: MIT License
Classifier: Operating System :: OS Independent
Classifier: Programming Language :: Python :: 3
Classifier: Topic :: Scientific/Engineering :: Atmospheric Science
Requires-Python: >=3.8
Requires-Dist: einops>=0.7.0
Requires-Dist: torch>=2.0.0
Requires-Dist: torchvision>=0.15.1
Provides-Extra: full
Requires-Dist: datasets>=2.11.0; extra == 'full'
Requires-Dist: einops>=0.7.0; extra == 'full'
Requires-Dist: gradio>=4.25.0; extra == 'full'
Requires-Dist: imageio[pyav]>=2.31.1; extra == 'full'
Requires-Dist: matplotlib>=3.7.1; extra == 'full'
Requires-Dist: numpy>=1.25.0; extra == 'full'
Requires-Dist: pandas>=2.0.0; extra == 'full'
Requires-Dist: tensorboard>=2.12.1; extra == 'full'
Requires-Dist: torch>=2.0.0; extra == 'full'
Requires-Dist: torchvision>=0.15.1; extra == 'full'
